{
  "date": "2026-12-23",
  "name_it": "XXIII dicembre",
  "name_en": "23rd December",
  "name_es": "23 de diciembre",
  "name_pt": "23 de dezembro",
  "feast_type_it": "feria",
  "feast_type_en": "ferial",
  "feast_type_es": "ferial",
  "feast_type_pt": "ferial",
  "bio_en": "",
  "wikipedia_url_en": "",
  "bio_it": "Papa Giovanni XXIII, nato Angelo Giuseppe Roncalli, è stato il 261º papa della Chiesa cattolica e vescovo di Roma, primate d'Italia e 3º sovrano dello Stato della Città del Vaticano, oltre agli altri titoli propri del romano pontefice, dal 28 ottobre 1958 fino alla morte.",
  "wikipedia_url_it": "https://it.wikipedia.org/wiki/Papa_Giovanni_XXIII",
  "bio_es": "El 23 de diciembre es el 357.º día del año en el calendario gregoriano y el 358.º en los años bisiestos. Quedan 8 días para finalizar el año.",
  "wikipedia_url_es": "https://es.wikipedia.org/wiki/23_de_diciembre",
  "bio_pt": "",
  "wikipedia_url_pt": "https://pt.wikipedia.org/wiki/23_de_dezembro"
}